[
  {
    "full_image_id": "image-3.jpg",
    "full_image_description": "This painting is a classic still life that features natural, restrained colors and realistic expression. It reflects the 17th–18th century European style, where food, fruits, ceramics, and glassware are carefully arranged to emphasize daily abundance and beauty.",
    "crops": [
      {
        "crop_id": "image-3_crop0.jpg",
        "crop_description": "A floral-patterned jug placed in the center. It features intricate ceramic decoration and is likely used for ornamental purposes."
      }
    ]
  },
  {
    "full_image_id": "image-2.jpg",
    "full_image_description": "A still life featuring a plate of lemons and grapes on a white cloth against a gray background. The vivid yellow lemons and deep purple grapes create a sharp contrast, evoking a simple yet elegant atmosphere.",
    "crops": [
      {
        "crop_id": "image-2_crop0.jpg",
        "crop_description": "A single lemon placed outside the plate"
      },
      {
        "crop_id": "image-2_crop1.jpg",
        "crop_description": "A single lemon placed outside the plate"
      },
      {
        "crop_id": "image-2_crop2.jpg",
        "crop_description": "A single lemon placed outside the plate"
      },
      {
        "crop_id": "image-2_crop3.jpg",
        "crop_description": "A single lemon placed outside the plate"
      }
    ]
  },
  {
    "full_image_id": "image-6.jpg",
    "full_image_description": "This still life depicts a dark glass bottle and three red pomegranates set against a gray background. The subdued colors and simple composition create a calm and refined mood.",
    "crops": [
      {
        "crop_id": "image-6_crop0.jpg",
        "crop_description": "A round red pomegranate placed at the front left"
      },
      {
        "crop_id": "image-6_crop1.jpg",
        "crop_description": "A dark glass bottle at the center with pomegranate reflection"
      },
      {
        "crop_id": "image-6_crop2.jpg",
        "crop_description": "Two red pomegranates placed side by side on the right"
      },
      {
        "crop_id": "image-6_crop3.jpg",
        "crop_description": "A round red pomegranate"
      },
      {
        "crop_id": "image-6_crop4.jpg",
        "crop_description": "Two red pomegranates placed side by side on the right"
      }
    ]
  },
  {
    "full_image_id": "image-7.jpg",
    "full_image_description": "A still life with wooden bowls, ripe pears, and flowers against a green background. The warm-colored fruits, brown pottery, and white blossoms blend naturally to evoke a serene atmosphere.",
    "crops": [
      {
        "crop_id": "image-7_crop0.jpg",
        "crop_description": "Curved ceramic jug placed on the right"
      },
      {
        "crop_id": "image-7_crop1.jpg",
        "crop_description": "A single reddish pear placed in the front left"
      },
      {
        "crop_id": "image-7_crop2.jpg",
        "crop_description": "A wide brown tray located in the center"
      },
      {
        "crop_id": "image-7_crop3.jpg",
        "crop_description": "Yellow pears in a bowl"
      },
      {
        "crop_id": "image-7_crop4.jpg",
        "crop_description": "A small brown cup at the far left of the painting"
      },
      {
        "crop_id": "image-7_crop5.jpg",
        "crop_description": "Gray table surface"
      },
      {
        "crop_id": "image-7_crop6.jpg",
        "crop_description": "A yellow-colored pear"
      },
      {
        "crop_id": "image-7_crop7.jpg",
        "crop_description": "Pears in a bowl"
      }
    ]
  },
  {
    "full_image_id": "image-4.jpg",
    "full_image_description": "This still life neatly arranges a flower vase, wine bottle, pomegranate, and small metal ornament on a table. The pink flowers and deep background contrast to create a calm and elegant ambiance.",
    "crops": [
      {
        "crop_id": "image-4_crop0.jpg",
        "crop_description": "Black wine bottle placed next to a flower vase"
      }
    ]
  },
  {
    "full_image_id": "image-5.jpeg",
    "full_image_description": "A still life where yellow bowls, a jug, peaches, and cloth are neatly placed on a table. The soft green background contrasts with yellow, orange, and white tones, producing a warm and orderly atmosphere.",
    "crops": [
      {
        "crop_id": "image-5_crop0.jpg",
        "crop_description": "Beige water jug placed in the center back"
      },
      {
        "crop_id": "image-5_crop1.jpg",
        "crop_description": "Two peaches placed on the left side of the table"
      },
      {
        "crop_id": "image-5_crop2.jpg",
        "crop_description": "Beige water jug placed in the center back"
      },
      {
        "crop_id": "image-5_crop3.jpg",
        "crop_description": "A yellow peach"
      }
    ]
  }
]
